CharsetFilter/CharsetFilter.py
CharsetFilter/__init__.py
CharsetFilter-1.0.3.dist-info/LICENSE.txt
CharsetFilter-1.0.3.dist-info/METADATA
CharsetFilter-1.0.3.dist-info/WHEEL
CharsetFilter-1.0.3.dist-info/entry_points.txt
CharsetFilter-1.0.3.dist-info/top_level.txt
CharsetFilter-1.0.3.dist-info/RECORD
