Metadata-Version: 2.1
Name: CharsetFilter
Version: 1.0.3
Summary: UNKNOWN
Home-page: https://github.com/xmxoxo/CharsetFilter
Author: He xi
Author-email: xmhexi@qq.com
License: UNKNOWN
Project-URL: Blog, https://blog.csdn.net/xmxoxo
Keywords: Chearset Filter tool
Platform: UNKNOWN
Classifier: Development Status :: 5 - Production/Stable
Classifier: Intended Audience :: Developers
Classifier: Topic :: Software Development :: Code Generators
Classifier: License :: OSI Approved :: MIT License
Classifier: Programming Language :: Python :: 3
Classifier: Programming Language :: Python :: 3.4
Classifier: Programming Language :: Python :: 3.5
Classifier: Programming Language :: Python :: 3.6
